CHANGES.txt
README.txt
bootstrap.py
setup.py
src/z3c/__init__.py
src/z3c.resource.egg-info/PKG-INFO
src/z3c.resource.egg-info/SOURCES.txt
src/z3c.resource.egg-info/dependency_links.txt
src/z3c.resource.egg-info/namespace_packages.txt
src/z3c.resource.egg-info/not-zip-safe
src/z3c.resource.egg-info/requires.txt
src/z3c.resource.egg-info/top_level.txt
src/z3c/resource/README.txt
src/z3c/resource/SETUP.cfg
src/z3c/resource/__init__.py
src/z3c/resource/adapter.py
src/z3c/resource/configure.zcml
src/z3c/resource/interfaces.py
src/z3c/resource/namespace.py
src/z3c/resource/proxy.py
src/z3c/resource/resource.py
src/z3c/resource/testing.py
src/z3c/resource/tests.py
src/z3c/resource/z3c.resource-configure.zcml
src/z3c/resource/browser/__init__.py
src/z3c/resource/browser/configure.zcml
src/z3c/resource/browser/resource.gif
src/z3c/resource/browser/tests.py
src/z3c/resource/browser/views.py
src/z3c/resource/browser/zmi.zcml
src/z3c/resource/generations/__init__.py
src/z3c/resource/generations/configure.zcml